{
 "absolute_value": 0,
 "align_labels_right": 0,
 "creation": "2024-06-08 12:52:45.501425",
 "custom_format": 0,
 "default_print_language": "en",
 "disabled": 0,
 "doc_type": "Rent Payment",
 "docstatus": 0,
 "doctype": "Print Format",
 "font_size": 14,
 "format_data": "[{\"fieldname\": \"print_heading_template\", \"fieldtype\": \"Custom HTML\", \"options\": \"<style>\\n    .print-heading {\\n    text-align: center;\\n}\\n</style>\\n<div class=\\\"print-heading\\\">\\t\\t\\t\\t<h2><div>Rent Payment Receipt</div><br><small class=\\\"sub-heading\\\"><strong>{{doc.name}}</strong></small>\\t\\t\\t\\t</h2></div>\"}, {\"fieldtype\": \"Section Break\", \"label\": \"\"}, {\"fieldtype\": \"Column Break\"}, {\"fieldname\": \"_custom_html\", \"print_hide\": 0, \"label\": \"Custom HTML\", \"fieldtype\": \"HTML\", \"options\": \"<style>\\n    \\n.row {\\n  display: flex;\\n}\\n\\n.column {\\n  flex: 50%;\\n  padding: 10px;\\n}\\n.column p{\\n    margin-top:20px;\\n}\\n\\n.bold {\\n  font-weight: bold;\\n}\\n\\n.not-bold {\\n  font-weight: normal;\\n}\\n\\n</style>\\n<div class=\\\"container\\\">\\n  <div class=\\\"row\\\">\\n    <div class=\\\"column\\\">\\n      <p><strong>Tenant:</strong> Willy--06-24-0011</p>\\n      <p><strong>Contract:</strong> vasha-shop-Willy--06-24-0011-12</p>\\n      <p><strong>Payment Date:</strong> 08-06-2024</p>\\n    </div>\\n    <div class=\\\"column\\\">\\n      <p><strong>Shop:</strong> vasha-shop</p>\\n      <p><strong><span class=\\\"bold\\\">From:</span></strong> <span class=\\\"not-bold\\\">08-06-2024</span></p>\\n      <p><strong><span class=\\\"bold\\\">To:</span></strong> <span class=\\\"not-bold\\\">07-07-2024</span></p>\\n    </div>\\n  </div>\\n  \\n  <div class=\\\"row\\\" style=\\\"margin-top:50px; font-size:16px\\\">\\n      <div class=\\\"column\\\">\\n                <p><strong>Payment Method:</strong> Cash</p>\\n\\n      </div>\\n      <div class=\\\"column\\\">\\n                <p><strong>Amount:</strong> Sh 35,000.00</p>\\n\\n      </div>\\n      </div>\\n</div>\\n\"}]",
 "idx": 0,
 "line_breaks": 0,
 "margin_bottom": 15.0,
 "margin_left": 15.0,
 "margin_right": 15.0,
 "margin_top": 15.0,
 "modified": "2024-06-08 13:40:08.922918",
 "modified_by": "Administrator",
 "module": "airport Shop Management",
 "name": "Tenants Payment Receipt",
 "owner": "Administrator",
 "page_number": "Hide",
 "print_designer": 0,
 "print_designer_template_app": "print_designer",
 "print_format_builder": 0,
 "print_format_builder_beta": 0,
 "print_format_type": "Jinja",
 "raw_printing": 0,
 "show_section_headings": 0,
 "standard": "Yes"
}